tf_focal_frequency_loss/__init__.py
tf_focal_frequency_loss/tf_focal_frequency_loss.py
tf_focal_frequency_loss-0.1.2.dist-info/LICENSE
tf_focal_frequency_loss-0.1.2.dist-info/WHEEL
tf_focal_frequency_loss-0.1.2.dist-info/METADATA
tf_focal_frequency_loss-0.1.2.dist-info/RECORD
