Metadata-Version: 2.1
Name: tf-focal-frequency-loss
Version: 0.1.2
Summary: Focal Frequency Loss for Image Reconstruction and Synthesis - Tensorflow Implementation
Author-email: Zoheb Abai <aglauocnv@relay.firefox.com>
Requires-Python: >=3.6
Classifier: License :: OSI Approved :: MIT License
Requires-Dist: tensorflow >=2.5.0
Project-URL: Home, https://github.com/ZohebAbai/tf-focal-frequency-loss
